package_name/__init__.py
package_name/filters.py
package_name/transformations.py
package_name/utils.py
package_renan_reis_v2-0.0.1.dist-info/METADATA
package_renan_reis_v2-0.0.1.dist-info/WHEEL
package_renan_reis_v2-0.0.1.dist-info/top_level.txt
package_renan_reis_v2-0.0.1.dist-info/RECORD
