Metadata-Version: 2.4
Name: package-renan-reis-v2
Version: 0.0.1
Summary: Pacote simples de processamento de imagens
Home-page: https://github.com/Nanre-33/simple-package-template
Author: Renan Reis
Author-email: renanreis.gomes@gmail.com
Classifier: Programming Language :: Python :: 3
Classifier: License :: OSI Approved :: MIT License
Classifier: Operating System :: OS Independent
Requires-Python: >=3.8
Dynamic: author
Dynamic: author-email
Dynamic: classifier
Dynamic: description
Dynamic: description-content-type
Dynamic: home-page
Dynamic: requires-python
Dynamic: summary
